<annotation>
	<folder></folder>
	<filename>2008_003611_jpg.rf.14cc5918052b40a39e751d39cf7233ea.jpg</filename>
	<path>2008_003611_jpg.rf.14cc5918052b40a39e751d39cf7233ea.jpg</path>
	<source>
		<database>roboflow.ai</database>
	</source>
	<size>
		<width>500</width>
		<height>375</height>
		<depth>3</depth>
	</size>
	<segmented>0</segmented>
	<object>
		<name>person</name>
		<pose>Unspecified</pose>
		<truncated>0</truncated>
		<difficult>0</difficult>
		<occluded>0</occluded>
		<bndbox>
			<xmin>97</xmin>
			<xmax>482</xmax>
			<ymin>1</ymin>
			<ymax>375</ymax>
		</bndbox>
	</object>
	<object>
		<name>person</name>
		<pose>Unspecified</pose>
		<truncated>0</truncated>
		<difficult>0</difficult>
		<occluded>0</occluded>
		<bndbox>
			<xmin>79</xmin>
			<xmax>247</xmax>
			<ymin>1</ymin>
			<ymax>272</ymax>
		</bndbox>
	</object>
</annotation>
