<annotation>
	<folder></folder>
	<filename>2008_000716_jpg.rf.5524a9f3f19a49b9f1eb85efdac3cc72.jpg</filename>
	<path>2008_000716_jpg.rf.5524a9f3f19a49b9f1eb85efdac3cc72.jpg</path>
	<source>
		<database>roboflow.ai</database>
	</source>
	<size>
		<width>500</width>
		<height>278</height>
		<depth>3</depth>
	</size>
	<segmented>0</segmented>
	<object>
		<name>aeroplane</name>
		<pose>Unspecified</pose>
		<truncated>0</truncated>
		<difficult>0</difficult>
		<occluded>0</occluded>
		<bndbox>
			<xmin>5</xmin>
			<xmax>277</xmax>
			<ymin>82</ymin>
			<ymax>175</ymax>
		</bndbox>
	</object>
	<object>
		<name>aeroplane</name>
		<pose>Unspecified</pose>
		<truncated>0</truncated>
		<difficult>0</difficult>
		<occluded>0</occluded>
		<bndbox>
			<xmin>298</xmin>
			<xmax>483</xmax>
			<ymin>116</ymin>
			<ymax>182</ymax>
		</bndbox>
	</object>
</annotation>
