<annotation>
	<folder></folder>
	<filename>2008_006924_jpg.rf.00b2e7d88310e451410b4317fe07ccf4.jpg</filename>
	<path>2008_006924_jpg.rf.00b2e7d88310e451410b4317fe07ccf4.jpg</path>
	<source>
		<database>roboflow.ai</database>
	</source>
	<size>
		<width>500</width>
		<height>333</height>
		<depth>3</depth>
	</size>
	<segmented>0</segmented>
	<object>
		<name>person</name>
		<pose>Unspecified</pose>
		<truncated>0</truncated>
		<difficult>0</difficult>
		<occluded>0</occluded>
		<bndbox>
			<xmin>1</xmin>
			<xmax>376</xmax>
			<ymin>172</ymin>
			<ymax>333</ymax>
		</bndbox>
	</object>
	<object>
		<name>bird</name>
		<pose>Unspecified</pose>
		<truncated>0</truncated>
		<difficult>0</difficult>
		<occluded>0</occluded>
		<bndbox>
			<xmin>132</xmin>
			<xmax>331</xmax>
			<ymin>89</ymin>
			<ymax>218</ymax>
		</bndbox>
	</object>
</annotation>
