<annotation>
	<folder></folder>
	<filename>2008_007410_jpg.rf.6558602c0c8f360cf19be07f441865e9.jpg</filename>
	<path>2008_007410_jpg.rf.6558602c0c8f360cf19be07f441865e9.jpg</path>
	<source>
		<database>roboflow.ai</database>
	</source>
	<size>
		<width>500</width>
		<height>375</height>
		<depth>3</depth>
	</size>
	<segmented>0</segmented>
	<object>
		<name>bicycle</name>
		<pose>Unspecified</pose>
		<truncated>0</truncated>
		<difficult>0</difficult>
		<occluded>0</occluded>
		<bndbox>
			<xmin>100</xmin>
			<xmax>347</xmax>
			<ymin>191</ymin>
			<ymax>346</ymax>
		</bndbox>
	</object>
	<object>
		<name>person</name>
		<pose>Unspecified</pose>
		<truncated>0</truncated>
		<difficult>0</difficult>
		<occluded>0</occluded>
		<bndbox>
			<xmin>230</xmin>
			<xmax>315</xmax>
			<ymin>90</ymin>
			<ymax>333</ymax>
		</bndbox>
	</object>
</annotation>
