<annotation>
	<folder></folder>
	<filename>2008_005558_jpg.rf.72c0264b8cddbffb211e9a9c86be55df.jpg</filename>
	<path>2008_005558_jpg.rf.72c0264b8cddbffb211e9a9c86be55df.jpg</path>
	<source>
		<database>roboflow.ai</database>
	</source>
	<size>
		<width>422</width>
		<height>500</height>
		<depth>3</depth>
	</size>
	<segmented>0</segmented>
	<object>
		<name>horse</name>
		<pose>Unspecified</pose>
		<truncated>0</truncated>
		<difficult>0</difficult>
		<occluded>0</occluded>
		<bndbox>
			<xmin>62</xmin>
			<xmax>389</xmax>
			<ymin>187</ymin>
			<ymax>410</ymax>
		</bndbox>
	</object>
	<object>
		<name>person</name>
		<pose>Unspecified</pose>
		<truncated>0</truncated>
		<difficult>0</difficult>
		<occluded>0</occluded>
		<bndbox>
			<xmin>136</xmin>
			<xmax>231</xmax>
			<ymin>79</ymin>
			<ymax>272</ymax>
		</bndbox>
	</object>
</annotation>
