<annotation>
	<folder></folder>
	<filename>2008_008619_jpg.rf.f76ec98d78a46ff5aa6a6efc4702738b.jpg</filename>
	<path>2008_008619_jpg.rf.f76ec98d78a46ff5aa6a6efc4702738b.jpg</path>
	<source>
		<database>roboflow.ai</database>
	</source>
	<size>
		<width>500</width>
		<height>333</height>
		<depth>3</depth>
	</size>
	<segmented>0</segmented>
	<object>
		<name>bicycle</name>
		<pose>Unspecified</pose>
		<truncated>0</truncated>
		<difficult>0</difficult>
		<occluded>0</occluded>
		<bndbox>
			<xmin>261</xmin>
			<xmax>500</xmax>
			<ymin>199</ymin>
			<ymax>333</ymax>
		</bndbox>
	</object>
	<object>
		<name>person</name>
		<pose>Unspecified</pose>
		<truncated>0</truncated>
		<difficult>0</difficult>
		<occluded>0</occluded>
		<bndbox>
			<xmin>17</xmin>
			<xmax>181</xmax>
			<ymin>25</ymin>
			<ymax>333</ymax>
		</bndbox>
	</object>
	<object>
		<name>person</name>
		<pose>Unspecified</pose>
		<truncated>0</truncated>
		<difficult>0</difficult>
		<occluded>0</occluded>
		<bndbox>
			<xmin>303</xmin>
			<xmax>445</xmax>
			<ymin>29</ymin>
			<ymax>333</ymax>
		</bndbox>
	</object>
	<object>
		<name>bicycle</name>
		<pose>Unspecified</pose>
		<truncated>0</truncated>
		<difficult>0</difficult>
		<occluded>0</occluded>
		<bndbox>
			<xmin>121</xmin>
			<xmax>254</xmax>
			<ymin>244</ymin>
			<ymax>333</ymax>
		</bndbox>
	</object>
</annotation>
