<annotation>
	<folder></folder>
	<filename>2008_005747_jpg.rf.1ce0d712fa984ae6a88b7532e7844171.jpg</filename>
	<path>2008_005747_jpg.rf.1ce0d712fa984ae6a88b7532e7844171.jpg</path>
	<source>
		<database>roboflow.ai</database>
	</source>
	<size>
		<width>375</width>
		<height>500</height>
		<depth>3</depth>
	</size>
	<segmented>0</segmented>
	<object>
		<name>car</name>
		<pose>Unspecified</pose>
		<truncated>0</truncated>
		<difficult>0</difficult>
		<occluded>0</occluded>
		<bndbox>
			<xmin>1</xmin>
			<xmax>369</xmax>
			<ymin>32</ymin>
			<ymax>500</ymax>
		</bndbox>
	</object>
</annotation>
