<annotation>
	<folder></folder>
	<filename>2009_002838_jpg.rf.6ad0f18b340a1ff6a85d3be0251f85a2.jpg</filename>
	<path>2009_002838_jpg.rf.6ad0f18b340a1ff6a85d3be0251f85a2.jpg</path>
	<source>
		<database>roboflow.ai</database>
	</source>
	<size>
		<width>500</width>
		<height>375</height>
		<depth>3</depth>
	</size>
	<segmented>0</segmented>
	<object>
		<name>train</name>
		<pose>Unspecified</pose>
		<truncated>0</truncated>
		<difficult>0</difficult>
		<occluded>0</occluded>
		<bndbox>
			<xmin>79</xmin>
			<xmax>477</xmax>
			<ymin>51</ymin>
			<ymax>335</ymax>
		</bndbox>
	</object>
	<object>
		<name>person</name>
		<pose>Unspecified</pose>
		<truncated>0</truncated>
		<difficult>0</difficult>
		<occluded>0</occluded>
		<bndbox>
			<xmin>48</xmin>
			<xmax>59</xmax>
			<ymin>150</ymin>
			<ymax>168</ymax>
		</bndbox>
	</object>
	<object>
		<name>person</name>
		<pose>Unspecified</pose>
		<truncated>0</truncated>
		<difficult>0</difficult>
		<occluded>0</occluded>
		<bndbox>
			<xmin>7</xmin>
			<xmax>15</xmax>
			<ymin>149</ymin>
			<ymax>169</ymax>
		</bndbox>
	</object>
</annotation>
