<annotation>
	<folder></folder>
	<filename>2009_002506_jpg.rf.46f123e7d7c13ef42b88a6c10fc06bb2.jpg</filename>
	<path>2009_002506_jpg.rf.46f123e7d7c13ef42b88a6c10fc06bb2.jpg</path>
	<source>
		<database>roboflow.ai</database>
	</source>
	<size>
		<width>500</width>
		<height>333</height>
		<depth>3</depth>
	</size>
	<segmented>0</segmented>
	<object>
		<name>boat</name>
		<pose>Unspecified</pose>
		<truncated>0</truncated>
		<difficult>0</difficult>
		<occluded>0</occluded>
		<bndbox>
			<xmin>1</xmin>
			<xmax>500</xmax>
			<ymin>16</ymin>
			<ymax>247</ymax>
		</bndbox>
	</object>
	<object>
		<name>person</name>
		<pose>Unspecified</pose>
		<truncated>0</truncated>
		<difficult>0</difficult>
		<occluded>0</occluded>
		<bndbox>
			<xmin>367</xmin>
			<xmax>397</xmax>
			<ymin>107</ymin>
			<ymax>141</ymax>
		</bndbox>
	</object>
	<object>
		<name>person</name>
		<pose>Unspecified</pose>
		<truncated>0</truncated>
		<difficult>0</difficult>
		<occluded>0</occluded>
		<bndbox>
			<xmin>181</xmin>
			<xmax>203</xmax>
			<ymin>47</ymin>
			<ymax>94</ymax>
		</bndbox>
	</object>
</annotation>
