<annotation>
	<folder></folder>
	<filename>2009_004181_jpg.rf.883ca23b984799dd29291289e3dce9d8.jpg</filename>
	<path>2009_004181_jpg.rf.883ca23b984799dd29291289e3dce9d8.jpg</path>
	<source>
		<database>roboflow.ai</database>
	</source>
	<size>
		<width>500</width>
		<height>375</height>
		<depth>3</depth>
	</size>
	<segmented>0</segmented>
	<object>
		<name>sheep</name>
		<pose>Unspecified</pose>
		<truncated>0</truncated>
		<difficult>0</difficult>
		<occluded>0</occluded>
		<bndbox>
			<xmin>1</xmin>
			<xmax>71</xmax>
			<ymin>1</ymin>
			<ymax>95</ymax>
		</bndbox>
	</object>
	<object>
		<name>sheep</name>
		<pose>Unspecified</pose>
		<truncated>0</truncated>
		<difficult>0</difficult>
		<occluded>0</occluded>
		<bndbox>
			<xmin>82</xmin>
			<xmax>222</xmax>
			<ymin>1</ymin>
			<ymax>56</ymax>
		</bndbox>
	</object>
	<object>
		<name>sheep</name>
		<pose>Unspecified</pose>
		<truncated>0</truncated>
		<difficult>0</difficult>
		<occluded>0</occluded>
		<bndbox>
			<xmin>36</xmin>
			<xmax>355</xmax>
			<ymin>1</ymin>
			<ymax>213</ymax>
		</bndbox>
	</object>
	<object>
		<name>person</name>
		<pose>Unspecified</pose>
		<truncated>0</truncated>
		<difficult>0</difficult>
		<occluded>0</occluded>
		<bndbox>
			<xmin>206</xmin>
			<xmax>422</xmax>
			<ymin>146</ymin>
			<ymax>375</ymax>
		</bndbox>
	</object>
	<object>
		<name>person</name>
		<pose>Unspecified</pose>
		<truncated>0</truncated>
		<difficult>0</difficult>
		<occluded>0</occluded>
		<bndbox>
			<xmin>420</xmin>
			<xmax>500</xmax>
			<ymin>1</ymin>
			<ymax>197</ymax>
		</bndbox>
	</object>
</annotation>
