<annotation>
	<folder></folder>
	<filename>2009_004154_jpg.rf.b8272828882bc78cb08a467373f7c210.jpg</filename>
	<path>2009_004154_jpg.rf.b8272828882bc78cb08a467373f7c210.jpg</path>
	<source>
		<database>roboflow.ai</database>
	</source>
	<size>
		<width>500</width>
		<height>375</height>
		<depth>3</depth>
	</size>
	<segmented>0</segmented>
	<object>
		<name>bottle</name>
		<pose>Unspecified</pose>
		<truncated>0</truncated>
		<difficult>0</difficult>
		<occluded>0</occluded>
		<bndbox>
			<xmin>9</xmin>
			<xmax>26</xmax>
			<ymin>88</ymin>
			<ymax>124</ymax>
		</bndbox>
	</object>
	<object>
		<name>chair</name>
		<pose>Unspecified</pose>
		<truncated>0</truncated>
		<difficult>0</difficult>
		<occluded>0</occluded>
		<bndbox>
			<xmin>12</xmin>
			<xmax>81</xmax>
			<ymin>135</ymin>
			<ymax>285</ymax>
		</bndbox>
	</object>
	<object>
		<name>diningtable</name>
		<pose>Unspecified</pose>
		<truncated>0</truncated>
		<difficult>0</difficult>
		<occluded>0</occluded>
		<bndbox>
			<xmin>1</xmin>
			<xmax>123</xmax>
			<ymin>99</ymin>
			<ymax>150</ymax>
		</bndbox>
	</object>
	<object>
		<name>person</name>
		<pose>Unspecified</pose>
		<truncated>0</truncated>
		<difficult>0</difficult>
		<occluded>0</occluded>
		<bndbox>
			<xmin>205</xmin>
			<xmax>265</xmax>
			<ymin>10</ymin>
			<ymax>179</ymax>
		</bndbox>
	</object>
	<object>
		<name>chair</name>
		<pose>Unspecified</pose>
		<truncated>0</truncated>
		<difficult>0</difficult>
		<occluded>0</occluded>
		<bndbox>
			<xmin>397</xmin>
			<xmax>426</xmax>
			<ymin>82</ymin>
			<ymax>152</ymax>
		</bndbox>
	</object>
	<object>
		<name>chair</name>
		<pose>Unspecified</pose>
		<truncated>0</truncated>
		<difficult>0</difficult>
		<occluded>0</occluded>
		<bndbox>
			<xmin>423</xmin>
			<xmax>484</xmax>
			<ymin>101</ymin>
			<ymax>202</ymax>
		</bndbox>
	</object>
	<object>
		<name>person</name>
		<pose>Unspecified</pose>
		<truncated>0</truncated>
		<difficult>0</difficult>
		<occluded>0</occluded>
		<bndbox>
			<xmin>414</xmin>
			<xmax>470</xmax>
			<ymin>23</ymin>
			<ymax>126</ymax>
		</bndbox>
	</object>
	<object>
		<name>person</name>
		<pose>Unspecified</pose>
		<truncated>0</truncated>
		<difficult>0</difficult>
		<occluded>0</occluded>
		<bndbox>
			<xmin>426</xmin>
			<xmax>500</xmax>
			<ymin>31</ymin>
			<ymax>165</ymax>
		</bndbox>
	</object>
	<object>
		<name>bottle</name>
		<pose>Unspecified</pose>
		<truncated>0</truncated>
		<difficult>0</difficult>
		<occluded>0</occluded>
		<bndbox>
			<xmin>222</xmin>
			<xmax>259</xmax>
			<ymin>303</ymin>
			<ymax>375</ymax>
		</bndbox>
	</object>
	<object>
		<name>chair</name>
		<pose>Unspecified</pose>
		<truncated>0</truncated>
		<difficult>0</difficult>
		<occluded>0</occluded>
		<bndbox>
			<xmin>434</xmin>
			<xmax>489</xmax>
			<ymin>157</ymin>
			<ymax>230</ymax>
		</bndbox>
	</object>
	<object>
		<name>diningtable</name>
		<pose>Unspecified</pose>
		<truncated>0</truncated>
		<difficult>0</difficult>
		<occluded>0</occluded>
		<bndbox>
			<xmin>49</xmin>
			<xmax>500</xmax>
			<ymin>217</ymin>
			<ymax>375</ymax>
		</bndbox>
	</object>
	<object>
		<name>person</name>
		<pose>Unspecified</pose>
		<truncated>0</truncated>
		<difficult>0</difficult>
		<occluded>0</occluded>
		<bndbox>
			<xmin>36</xmin>
			<xmax>230</xmax>
			<ymin>49</ymin>
			<ymax>301</ymax>
		</bndbox>
	</object>
	<object>
		<name>person</name>
		<pose>Unspecified</pose>
		<truncated>0</truncated>
		<difficult>0</difficult>
		<occluded>0</occluded>
		<bndbox>
			<xmin>244</xmin>
			<xmax>399</xmax>
			<ymin>58</ymin>
			<ymax>264</ymax>
		</bndbox>
	</object>
</annotation>
