<annotation>
	<folder></folder>
	<filename>2009_000398_jpg.rf.600464dbe777e0cc82fe18882c4689f9.jpg</filename>
	<path>2009_000398_jpg.rf.600464dbe777e0cc82fe18882c4689f9.jpg</path>
	<source>
		<database>roboflow.ai</database>
	</source>
	<size>
		<width>400</width>
		<height>500</height>
		<depth>3</depth>
	</size>
	<segmented>0</segmented>
	<object>
		<name>tvmonitor</name>
		<pose>Unspecified</pose>
		<truncated>0</truncated>
		<difficult>0</difficult>
		<occluded>0</occluded>
		<bndbox>
			<xmin>89</xmin>
			<xmax>275</xmax>
			<ymin>338</ymin>
			<ymax>500</ymax>
		</bndbox>
	</object>
	<object>
		<name>tvmonitor</name>
		<pose>Unspecified</pose>
		<truncated>0</truncated>
		<difficult>0</difficult>
		<occluded>0</occluded>
		<bndbox>
			<xmin>182</xmin>
			<xmax>225</xmax>
			<ymin>307</ymin>
			<ymax>325</ymax>
		</bndbox>
	</object>
	<object>
		<name>tvmonitor</name>
		<pose>Unspecified</pose>
		<truncated>0</truncated>
		<difficult>0</difficult>
		<occluded>0</occluded>
		<bndbox>
			<xmin>142</xmin>
			<xmax>231</xmax>
			<ymin>324</ymin>
			<ymax>349</ymax>
		</bndbox>
	</object>
</annotation>
