<annotation>
	<folder></folder>
	<filename>2009_001368_jpg.rf.0c8c7d4c058bd46e22b18f66091fa102.jpg</filename>
	<path>2009_001368_jpg.rf.0c8c7d4c058bd46e22b18f66091fa102.jpg</path>
	<source>
		<database>roboflow.ai</database>
	</source>
	<size>
		<width>500</width>
		<height>333</height>
		<depth>3</depth>
	</size>
	<segmented>0</segmented>
	<object>
		<name>dog</name>
		<pose>Unspecified</pose>
		<truncated>0</truncated>
		<difficult>0</difficult>
		<occluded>0</occluded>
		<bndbox>
			<xmin>124</xmin>
			<xmax>381</xmax>
			<ymin>78</ymin>
			<ymax>333</ymax>
		</bndbox>
	</object>
	<object>
		<name>dog</name>
		<pose>Unspecified</pose>
		<truncated>0</truncated>
		<difficult>0</difficult>
		<occluded>0</occluded>
		<bndbox>
			<xmin>21</xmin>
			<xmax>211</xmax>
			<ymin>81</ymin>
			<ymax>333</ymax>
		</bndbox>
	</object>
</annotation>
