<annotation>
	<folder></folder>
	<filename>2009_003044_jpg.rf.f8879642950dedf6bf27d074ac2afefc.jpg</filename>
	<path>2009_003044_jpg.rf.f8879642950dedf6bf27d074ac2afefc.jpg</path>
	<source>
		<database>roboflow.ai</database>
	</source>
	<size>
		<width>500</width>
		<height>372</height>
		<depth>3</depth>
	</size>
	<segmented>0</segmented>
	<object>
		<name>aeroplane</name>
		<pose>Unspecified</pose>
		<truncated>0</truncated>
		<difficult>0</difficult>
		<occluded>0</occluded>
		<bndbox>
			<xmin>39</xmin>
			<xmax>500</xmax>
			<ymin>38</ymin>
			<ymax>372</ymax>
		</bndbox>
	</object>
	<object>
		<name>person</name>
		<pose>Unspecified</pose>
		<truncated>0</truncated>
		<difficult>0</difficult>
		<occluded>0</occluded>
		<bndbox>
			<xmin>107</xmin>
			<xmax>489</xmax>
			<ymin>63</ymin>
			<ymax>372</ymax>
		</bndbox>
	</object>
</annotation>
