<annotation>
	<folder></folder>
	<filename>2009_001648_jpg.rf.3a91eff121926434f787d0128895277b.jpg</filename>
	<path>2009_001648_jpg.rf.3a91eff121926434f787d0128895277b.jpg</path>
	<source>
		<database>roboflow.ai</database>
	</source>
	<size>
		<width>500</width>
		<height>315</height>
		<depth>3</depth>
	</size>
	<segmented>0</segmented>
	<object>
		<name>train</name>
		<pose>Unspecified</pose>
		<truncated>0</truncated>
		<difficult>0</difficult>
		<occluded>0</occluded>
		<bndbox>
			<xmin>237</xmin>
			<xmax>404</xmax>
			<ymin>100</ymin>
			<ymax>221</ymax>
		</bndbox>
	</object>
	<object>
		<name>train</name>
		<pose>Unspecified</pose>
		<truncated>0</truncated>
		<difficult>0</difficult>
		<occluded>0</occluded>
		<bndbox>
			<xmin>473</xmin>
			<xmax>500</xmax>
			<ymin>134</ymin>
			<ymax>194</ymax>
		</bndbox>
	</object>
	<object>
		<name>train</name>
		<pose>Unspecified</pose>
		<truncated>0</truncated>
		<difficult>0</difficult>
		<occluded>0</occluded>
		<bndbox>
			<xmin>2</xmin>
			<xmax>189</xmax>
			<ymin>44</ymin>
			<ymax>269</ymax>
		</bndbox>
	</object>
</annotation>
