<annotation>
	<folder></folder>
	<filename>2009_003944_jpg.rf.eba639f9920f1ca5c81b3a56978006bc.jpg</filename>
	<path>2009_003944_jpg.rf.eba639f9920f1ca5c81b3a56978006bc.jpg</path>
	<source>
		<database>roboflow.ai</database>
	</source>
	<size>
		<width>500</width>
		<height>375</height>
		<depth>3</depth>
	</size>
	<segmented>0</segmented>
	<object>
		<name>motorbike</name>
		<pose>Unspecified</pose>
		<truncated>0</truncated>
		<difficult>0</difficult>
		<occluded>0</occluded>
		<bndbox>
			<xmin>1</xmin>
			<xmax>500</xmax>
			<ymin>1</ymin>
			<ymax>375</ymax>
		</bndbox>
	</object>
</annotation>
