<annotation>
	<folder></folder>
	<filename>2009_001633_jpg.rf.3dd3a4b40697d69677f11e6c81b84a83.jpg</filename>
	<path>2009_001633_jpg.rf.3dd3a4b40697d69677f11e6c81b84a83.jpg</path>
	<source>
		<database>roboflow.ai</database>
	</source>
	<size>
		<width>375</width>
		<height>500</height>
		<depth>3</depth>
	</size>
	<segmented>0</segmented>
	<object>
		<name>bus</name>
		<pose>Unspecified</pose>
		<truncated>0</truncated>
		<difficult>0</difficult>
		<occluded>0</occluded>
		<bndbox>
			<xmin>20</xmin>
			<xmax>346</xmax>
			<ymin>16</ymin>
			<ymax>497</ymax>
		</bndbox>
	</object>
	<object>
		<name>bus</name>
		<pose>Unspecified</pose>
		<truncated>0</truncated>
		<difficult>0</difficult>
		<occluded>0</occluded>
		<bndbox>
			<xmin>304</xmin>
			<xmax>375</xmax>
			<ymin>153</ymin>
			<ymax>386</ymax>
		</bndbox>
	</object>
</annotation>
