<annotation>
	<folder></folder>
	<filename>2009_000318_jpg.rf.d768dbe1ab02b9444e305c526d947488.jpg</filename>
	<path>2009_000318_jpg.rf.d768dbe1ab02b9444e305c526d947488.jpg</path>
	<source>
		<database>roboflow.ai</database>
	</source>
	<size>
		<width>500</width>
		<height>375</height>
		<depth>3</depth>
	</size>
	<segmented>0</segmented>
	<object>
		<name>bird</name>
		<pose>Unspecified</pose>
		<truncated>0</truncated>
		<difficult>0</difficult>
		<occluded>0</occluded>
		<bndbox>
			<xmin>199</xmin>
			<xmax>294</xmax>
			<ymin>124</ymin>
			<ymax>225</ymax>
		</bndbox>
	</object>
	<object>
		<name>bird</name>
		<pose>Unspecified</pose>
		<truncated>0</truncated>
		<difficult>0</difficult>
		<occluded>0</occluded>
		<bndbox>
			<xmin>1</xmin>
			<xmax>109</xmax>
			<ymin>1</ymin>
			<ymax>165</ymax>
		</bndbox>
	</object>
</annotation>
