<annotation>
	<folder></folder>
	<filename>2009_001770_jpg.rf.7cbd1155fbd576707ac59c61e77ff515.jpg</filename>
	<path>2009_001770_jpg.rf.7cbd1155fbd576707ac59c61e77ff515.jpg</path>
	<source>
		<database>roboflow.ai</database>
	</source>
	<size>
		<width>500</width>
		<height>374</height>
		<depth>3</depth>
	</size>
	<segmented>0</segmented>
	<object>
		<name>boat</name>
		<pose>Unspecified</pose>
		<truncated>0</truncated>
		<difficult>0</difficult>
		<occluded>0</occluded>
		<bndbox>
			<xmin>161</xmin>
			<xmax>250</xmax>
			<ymin>171</ymin>
			<ymax>237</ymax>
		</bndbox>
	</object>
	<object>
		<name>boat</name>
		<pose>Unspecified</pose>
		<truncated>0</truncated>
		<difficult>0</difficult>
		<occluded>0</occluded>
		<bndbox>
			<xmin>441</xmin>
			<xmax>500</xmax>
			<ymin>126</ymin>
			<ymax>301</ymax>
		</bndbox>
	</object>
</annotation>
