<annotation>
	<folder></folder>
	<filename>2009_002732_jpg.rf.0fd259482cc9b17a54eacc796889067d.jpg</filename>
	<path>2009_002732_jpg.rf.0fd259482cc9b17a54eacc796889067d.jpg</path>
	<source>
		<database>roboflow.ai</database>
	</source>
	<size>
		<width>500</width>
		<height>333</height>
		<depth>3</depth>
	</size>
	<segmented>0</segmented>
	<object>
		<name>sofa</name>
		<pose>Unspecified</pose>
		<truncated>0</truncated>
		<difficult>0</difficult>
		<occluded>0</occluded>
		<bndbox>
			<xmin>1</xmin>
			<xmax>500</xmax>
			<ymin>1</ymin>
			<ymax>333</ymax>
		</bndbox>
	</object>
	<object>
		<name>person</name>
		<pose>Unspecified</pose>
		<truncated>0</truncated>
		<difficult>0</difficult>
		<occluded>0</occluded>
		<bndbox>
			<xmin>65</xmin>
			<xmax>430</xmax>
			<ymin>135</ymin>
			<ymax>333</ymax>
		</bndbox>
	</object>
	<object>
		<name>person</name>
		<pose>Unspecified</pose>
		<truncated>0</truncated>
		<difficult>0</difficult>
		<occluded>0</occluded>
		<bndbox>
			<xmin>147</xmin>
			<xmax>461</xmax>
			<ymin>1</ymin>
			<ymax>333</ymax>
		</bndbox>
	</object>
	<object>
		<name>bottle</name>
		<pose>Unspecified</pose>
		<truncated>0</truncated>
		<difficult>0</difficult>
		<occluded>0</occluded>
		<bndbox>
			<xmin>208</xmin>
			<xmax>320</xmax>
			<ymin>204</ymin>
			<ymax>274</ymax>
		</bndbox>
	</object>
</annotation>
