<annotation>
	<folder></folder>
	<filename>2010_000498_jpg.rf.8989642c6654a1c276e863ed06e2c8e2.jpg</filename>
	<path>2010_000498_jpg.rf.8989642c6654a1c276e863ed06e2c8e2.jpg</path>
	<source>
		<database>roboflow.ai</database>
	</source>
	<size>
		<width>500</width>
		<height>405</height>
		<depth>3</depth>
	</size>
	<segmented>0</segmented>
	<object>
		<name>cow</name>
		<pose>Unspecified</pose>
		<truncated>0</truncated>
		<difficult>0</difficult>
		<occluded>0</occluded>
		<bndbox>
			<xmin>133</xmin>
			<xmax>393</xmax>
			<ymin>104</ymin>
			<ymax>363</ymax>
		</bndbox>
	</object>
</annotation>
