<annotation>
	<folder></folder>
	<filename>2010_003635_jpg.rf.4ff6c8f0b14cdb75b34517bebdc69fa9.jpg</filename>
	<path>2010_003635_jpg.rf.4ff6c8f0b14cdb75b34517bebdc69fa9.jpg</path>
	<source>
		<database>roboflow.ai</database>
	</source>
	<size>
		<width>500</width>
		<height>335</height>
		<depth>3</depth>
	</size>
	<segmented>0</segmented>
	<object>
		<name>motorbike</name>
		<pose>Unspecified</pose>
		<truncated>0</truncated>
		<difficult>0</difficult>
		<occluded>0</occluded>
		<bndbox>
			<xmin>38</xmin>
			<xmax>440</xmax>
			<ymin>32</ymin>
			<ymax>273</ymax>
		</bndbox>
	</object>
	<object>
		<name>car</name>
		<pose>Unspecified</pose>
		<truncated>0</truncated>
		<difficult>0</difficult>
		<occluded>0</occluded>
		<bndbox>
			<xmin>1</xmin>
			<xmax>162</xmax>
			<ymin>27</ymin>
			<ymax>151</ymax>
		</bndbox>
	</object>
	<object>
		<name>bus</name>
		<pose>Unspecified</pose>
		<truncated>0</truncated>
		<difficult>0</difficult>
		<occluded>0</occluded>
		<bndbox>
			<xmin>150</xmin>
			<xmax>478</xmax>
			<ymin>1</ymin>
			<ymax>123</ymax>
		</bndbox>
	</object>
</annotation>
