<annotation>
	<folder></folder>
	<filename>2010_004105_jpg.rf.fdc23020054b4fe90054fedb334d5371.jpg</filename>
	<path>2010_004105_jpg.rf.fdc23020054b4fe90054fedb334d5371.jpg</path>
	<source>
		<database>roboflow.ai</database>
	</source>
	<size>
		<width>500</width>
		<height>375</height>
		<depth>3</depth>
	</size>
	<segmented>0</segmented>
	<object>
		<name>sheep</name>
		<pose>Unspecified</pose>
		<truncated>0</truncated>
		<difficult>0</difficult>
		<occluded>0</occluded>
		<bndbox>
			<xmin>122</xmin>
			<xmax>371</xmax>
			<ymin>46</ymin>
			<ymax>374</ymax>
		</bndbox>
	</object>
</annotation>
