<annotation>
	<folder></folder>
	<filename>2010_004179_jpg.rf.4629769ca495dae6b73a22418a5a6504.jpg</filename>
	<path>2010_004179_jpg.rf.4629769ca495dae6b73a22418a5a6504.jpg</path>
	<source>
		<database>roboflow.ai</database>
	</source>
	<size>
		<width>500</width>
		<height>375</height>
		<depth>3</depth>
	</size>
	<segmented>0</segmented>
	<object>
		<name>dog</name>
		<pose>Unspecified</pose>
		<truncated>0</truncated>
		<difficult>0</difficult>
		<occluded>0</occluded>
		<bndbox>
			<xmin>16</xmin>
			<xmax>500</xmax>
			<ymin>54</ymin>
			<ymax>289</ymax>
		</bndbox>
	</object>
</annotation>
