<annotation>
	<folder></folder>
	<filename>2010_001574_jpg.rf.7a35da148e3be518020944e5742ac70b.jpg</filename>
	<path>2010_001574_jpg.rf.7a35da148e3be518020944e5742ac70b.jpg</path>
	<source>
		<database>roboflow.ai</database>
	</source>
	<size>
		<width>500</width>
		<height>375</height>
		<depth>3</depth>
	</size>
	<segmented>0</segmented>
	<object>
		<name>chair</name>
		<pose>Unspecified</pose>
		<truncated>0</truncated>
		<difficult>0</difficult>
		<occluded>0</occluded>
		<bndbox>
			<xmin>54</xmin>
			<xmax>134</xmax>
			<ymin>119</ymin>
			<ymax>219</ymax>
		</bndbox>
	</object>
	<object>
		<name>chair</name>
		<pose>Unspecified</pose>
		<truncated>0</truncated>
		<difficult>0</difficult>
		<occluded>0</occluded>
		<bndbox>
			<xmin>125</xmin>
			<xmax>214</xmax>
			<ymin>124</ymin>
			<ymax>250</ymax>
		</bndbox>
	</object>
</annotation>
