<annotation>
	<folder></folder>
	<filename>2010_001863_jpg.rf.dfe2b64792a624d467a3b1660f1d54f6.jpg</filename>
	<path>2010_001863_jpg.rf.dfe2b64792a624d467a3b1660f1d54f6.jpg</path>
	<source>
		<database>roboflow.ai</database>
	</source>
	<size>
		<width>375</width>
		<height>500</height>
		<depth>3</depth>
	</size>
	<segmented>0</segmented>
	<object>
		<name>cat</name>
		<pose>Unspecified</pose>
		<truncated>0</truncated>
		<difficult>0</difficult>
		<occluded>0</occluded>
		<bndbox>
			<xmin>1</xmin>
			<xmax>340</xmax>
			<ymin>85</ymin>
			<ymax>433</ymax>
		</bndbox>
	</object>
</annotation>
