<annotation>
	<folder></folder>
	<filename>2011_001589_jpg.rf.7b21dff14e4dc60b6a9e822680e58b96.jpg</filename>
	<path>2011_001589_jpg.rf.7b21dff14e4dc60b6a9e822680e58b96.jpg</path>
	<source>
		<database>roboflow.ai</database>
	</source>
	<size>
		<width>500</width>
		<height>333</height>
		<depth>3</depth>
	</size>
	<segmented>0</segmented>
	<object>
		<name>boat</name>
		<pose>Unspecified</pose>
		<truncated>0</truncated>
		<difficult>0</difficult>
		<occluded>0</occluded>
		<bndbox>
			<xmin>137</xmin>
			<xmax>344</xmax>
			<ymin>117</ymin>
			<ymax>173</ymax>
		</bndbox>
	</object>
	<object>
		<name>boat</name>
		<pose>Unspecified</pose>
		<truncated>0</truncated>
		<difficult>0</difficult>
		<occluded>0</occluded>
		<bndbox>
			<xmin>447</xmin>
			<xmax>498</xmax>
			<ymin>157</ymin>
			<ymax>178</ymax>
		</bndbox>
	</object>
	<object>
		<name>boat</name>
		<pose>Unspecified</pose>
		<truncated>0</truncated>
		<difficult>0</difficult>
		<occluded>0</occluded>
		<bndbox>
			<xmin>67</xmin>
			<xmax>85</xmax>
			<ymin>162</ymin>
			<ymax>176</ymax>
		</bndbox>
	</object>
</annotation>
