<annotation>
	<folder></folder>
	<filename>2011_002640_jpg.rf.e2c82ebeb29ec6640e427ccc58bd35cc.jpg</filename>
	<path>2011_002640_jpg.rf.e2c82ebeb29ec6640e427ccc58bd35cc.jpg</path>
	<source>
		<database>roboflow.ai</database>
	</source>
	<size>
		<width>500</width>
		<height>333</height>
		<depth>3</depth>
	</size>
	<segmented>0</segmented>
	<object>
		<name>bottle</name>
		<pose>Unspecified</pose>
		<truncated>0</truncated>
		<difficult>0</difficult>
		<occluded>0</occluded>
		<bndbox>
			<xmin>238</xmin>
			<xmax>251</xmax>
			<ymin>165</ymin>
			<ymax>204</ymax>
		</bndbox>
	</object>
	<object>
		<name>chair</name>
		<pose>Unspecified</pose>
		<truncated>0</truncated>
		<difficult>0</difficult>
		<occluded>0</occluded>
		<bndbox>
			<xmin>350</xmin>
			<xmax>431</xmax>
			<ymin>244</ymin>
			<ymax>333</ymax>
		</bndbox>
	</object>
	<object>
		<name>chair</name>
		<pose>Unspecified</pose>
		<truncated>0</truncated>
		<difficult>0</difficult>
		<occluded>0</occluded>
		<bndbox>
			<xmin>46</xmin>
			<xmax>153</xmax>
			<ymin>218</ymin>
			<ymax>333</ymax>
		</bndbox>
	</object>
	<object>
		<name>chair</name>
		<pose>Unspecified</pose>
		<truncated>0</truncated>
		<difficult>0</difficult>
		<occluded>0</occluded>
		<bndbox>
			<xmin>1</xmin>
			<xmax>12</xmax>
			<ymin>186</ymin>
			<ymax>243</ymax>
		</bndbox>
	</object>
	<object>
		<name>diningtable</name>
		<pose>Unspecified</pose>
		<truncated>0</truncated>
		<difficult>0</difficult>
		<occluded>0</occluded>
		<bndbox>
			<xmin>149</xmin>
			<xmax>361</xmax>
			<ymin>198</ymin>
			<ymax>333</ymax>
		</bndbox>
	</object>
	<object>
		<name>chair</name>
		<pose>Unspecified</pose>
		<truncated>0</truncated>
		<difficult>0</difficult>
		<occluded>0</occluded>
		<bndbox>
			<xmin>1</xmin>
			<xmax>62</xmax>
			<ymin>177</ymin>
			<ymax>329</ymax>
		</bndbox>
	</object>
	<object>
		<name>person</name>
		<pose>Unspecified</pose>
		<truncated>0</truncated>
		<difficult>0</difficult>
		<occluded>0</occluded>
		<bndbox>
			<xmin>347</xmin>
			<xmax>452</xmax>
			<ymin>106</ymin>
			<ymax>286</ymax>
		</bndbox>
	</object>
	<object>
		<name>person</name>
		<pose>Unspecified</pose>
		<truncated>0</truncated>
		<difficult>0</difficult>
		<occluded>0</occluded>
		<bndbox>
			<xmin>128</xmin>
			<xmax>209</xmax>
			<ymin>124</ymin>
			<ymax>250</ymax>
		</bndbox>
	</object>
	<object>
		<name>person</name>
		<pose>Unspecified</pose>
		<truncated>0</truncated>
		<difficult>0</difficult>
		<occluded>0</occluded>
		<bndbox>
			<xmin>53</xmin>
			<xmax>221</xmax>
			<ymin>130</ymin>
			<ymax>333</ymax>
		</bndbox>
	</object>
</annotation>
