<annotation>
	<folder></folder>
	<filename>2011_005938_jpg.rf.27a122f58220826f30f85ec6e54123e6.jpg</filename>
	<path>2011_005938_jpg.rf.27a122f58220826f30f85ec6e54123e6.jpg</path>
	<source>
		<database>roboflow.ai</database>
	</source>
	<size>
		<width>500</width>
		<height>330</height>
		<depth>3</depth>
	</size>
	<segmented>0</segmented>
	<object>
		<name>person</name>
		<pose>Unspecified</pose>
		<truncated>0</truncated>
		<difficult>0</difficult>
		<occluded>0</occluded>
		<bndbox>
			<xmin>235</xmin>
			<xmax>280</xmax>
			<ymin>137</ymin>
			<ymax>218</ymax>
		</bndbox>
	</object>
</annotation>
