<annotation>
	<folder></folder>
	<filename>2011_003410_jpg.rf.103596a1edacd1acb313031fc261913d.jpg</filename>
	<path>2011_003410_jpg.rf.103596a1edacd1acb313031fc261913d.jpg</path>
	<source>
		<database>roboflow.ai</database>
	</source>
	<size>
		<width>375</width>
		<height>500</height>
		<depth>3</depth>
	</size>
	<segmented>0</segmented>
	<object>
		<name>person</name>
		<pose>Unspecified</pose>
		<truncated>0</truncated>
		<difficult>0</difficult>
		<occluded>0</occluded>
		<bndbox>
			<xmin>171</xmin>
			<xmax>375</xmax>
			<ymin>53</ymin>
			<ymax>500</ymax>
		</bndbox>
	</object>
	<object>
		<name>person</name>
		<pose>Unspecified</pose>
		<truncated>0</truncated>
		<difficult>0</difficult>
		<occluded>0</occluded>
		<bndbox>
			<xmin>1</xmin>
			<xmax>187</xmax>
			<ymin>58</ymin>
			<ymax>500</ymax>
		</bndbox>
	</object>
</annotation>
