<annotation>
	<folder></folder>
	<filename>2011_003727_jpg.rf.025f53074450ecf5dc3ac3bba80fc4d8.jpg</filename>
	<path>2011_003727_jpg.rf.025f53074450ecf5dc3ac3bba80fc4d8.jpg</path>
	<source>
		<database>roboflow.ai</database>
	</source>
	<size>
		<width>500</width>
		<height>396</height>
		<depth>3</depth>
	</size>
	<segmented>0</segmented>
	<object>
		<name>person</name>
		<pose>Unspecified</pose>
		<truncated>0</truncated>
		<difficult>0</difficult>
		<occluded>0</occluded>
		<bndbox>
			<xmin>135</xmin>
			<xmax>229</xmax>
			<ymin>67</ymin>
			<ymax>214</ymax>
		</bndbox>
	</object>
	<object>
		<name>person</name>
		<pose>Unspecified</pose>
		<truncated>0</truncated>
		<difficult>0</difficult>
		<occluded>0</occluded>
		<bndbox>
			<xmin>224</xmin>
			<xmax>325</xmax>
			<ymin>84</ymin>
			<ymax>274</ymax>
		</bndbox>
	</object>
</annotation>
