<annotation>
	<folder></folder>
	<filename>2012_002408_jpg.rf.814d7843a491789f1015582e3ce5ff08.jpg</filename>
	<path>2012_002408_jpg.rf.814d7843a491789f1015582e3ce5ff08.jpg</path>
	<source>
		<database>roboflow.ai</database>
	</source>
	<size>
		<width>500</width>
		<height>375</height>
		<depth>3</depth>
	</size>
	<segmented>0</segmented>
	<object>
		<name>person</name>
		<pose>Unspecified</pose>
		<truncated>0</truncated>
		<difficult>0</difficult>
		<occluded>0</occluded>
		<bndbox>
			<xmin>196</xmin>
			<xmax>500</xmax>
			<ymin>56</ymin>
			<ymax>375</ymax>
		</bndbox>
	</object>
</annotation>
